grss-4.5.3.dist-info/RECORD
grss-4.5.3.dist-info/WHEEL
grss-4.5.3.dist-info/top_level.txt
grss-4.5.3.dist-info/METADATA
grss-4.5.3.dist-info/licenses/LICENSE
include/simulation.h
include/elements.h
include/spk.h
include/timeconvert.h
include/pck.h
include/grss.h
include/utilities.h
include/interpolate.h
include/observe.h
include/stm.h
include/force.h
include/ias15.h
include/parallel.h
include/approach.h
tests/python/run_tests.sh
tests/python/prop/didymos.ipynb
tests/python/prop/icarus.ipynb
tests/python/prop/moshup.ipynb
tests/python/prop/apophis.ipynb
tests/python/fit/farnocchia.ipynb
tests/python/fit/chesley.ipynb
tests/python/fit/eggl.ipynb
tests/python/fit/shantanunaidu.ipynb
tests/cpp/prop/pck_map.out
tests/cpp/prop/CMakeLists.txt
tests/cpp/prop/didymos.out
tests/cpp/prop/apophis.out
tests/cpp/prop/spk_map.cpp
tests/cpp/prop/spk_map.out
tests/cpp/prop/didymos.cpp
tests/cpp/prop/apophis.cpp
tests/cpp/prop/pck_map.cpp
docs/source/conf.py
grss/libgrss.cpython-313-darwin.so
grss/libgrss.a
grss/__init__.py
grss/utils.py
grss/version.txt
grss/kernels/get_kernels.py
grss/prop/prop_parallel.py
grss/prop/__init__.py
grss/prop/prop_utils.py
grss/prop/prop_unscented.py
grss/debias/get_debiasing_data.py
grss/fit/fit_simulation.py
grss/fit/fit_utils.py
grss/fit/__init__.py
grss/fit/fit_radar.py
grss/fit/fit_optical.py
grss/fit/fit_ades.py
grss/.dylibs/libstdc++.6.dylib
grss/.dylibs/libgcc_s.1.1.dylib
grss/.dylibs/libgomp.1.dylib
extern/get_cspice.py
src/elements.cpp
src/stm.cpp
src/CMakeLists.txt
src/parallel.cpp
src/grss.cpp
src/utilities.cpp
src/pck.cpp
src/interpolate.cpp
src/spk.cpp
src/ias15.cpp
src/observe.cpp
src/approach.cpp
src/timeconvert.cpp
src/simulation.cpp
src/force.cpp
