Metadata-Version: 2.4
Name: grss
Version: 4.5.3
Summary: GRSS: Gauss-Radau Small-body Simulator
Author: Rahil Makadia
Author-email: makadia2@illinois.edu
Maintainer: Rahil Makadia
Maintainer-email: makadia2@illinois.edu
License:                     GNU GENERAL PUBLIC LICENSE
Project-URL: Homepage, https://github.com/rahil-makadia/grss
Project-URL: Documentation, https://rahil-makadia.github.io/grss/
Project-URL: Source Code, https://github.com/rahil-makadia/grss
Project-URL: Bug Reports, https://github.com/rahil-makadia/grss/issues
Keywords: astronomy,asteroids,comets,orbit determination,orbit propagation
Classifier: Development Status :: 5 - Production/Stable
Classifier: Intended Audience :: Science/Research
Classifier: License :: OSI Approved :: GNU General Public License v3 (GPLv3)
Classifier: Natural Language :: English
Classifier: Operating System :: MacOS :: MacOS X
Classifier: Operating System :: POSIX :: Linux
Classifier: Operating System :: Unix
Classifier: Programming Language :: C++
Classifier: Programming Language :: Python :: 3
Classifier: Programming Language :: Python :: 3 :: Only
Classifier: Programming Language :: Python :: 3.8
Classifier: Programming Language :: Python :: 3.9
Classifier: Programming Language :: Python :: 3.10
Classifier: Programming Language :: Python :: 3.11
Classifier: Programming Language :: Python :: 3.12
Classifier: Topic :: Scientific/Engineering :: Astronomy
Requires-Python: >=3.10
License-File: LICENSE
Requires-Dist: astropy>=5.0
Requires-Dist: astroquery>=0.4.0
Requires-Dist: basemap>=1.4.0
Requires-Dist: healpy>=1.16.0
Requires-Dist: lxml>=5.1.0
Requires-Dist: matplotlib>=3.3.0
Requires-Dist: numba>=0.55.0
Requires-Dist: numpy!=2.3.*,>=1.22.0
Requires-Dist: pandas>=1.5.0
Requires-Dist: pybind11[global]>=2.10.0
Requires-Dist: requests>=2.22.0
Requires-Dist: tqdm>=4.65.0
Dynamic: license-file
